iaflow/__init__.py
iaflow-2.3.0.dist-info/LICENSE
iaflow-2.3.0.dist-info/METADATA
iaflow-2.3.0.dist-info/WHEEL
iaflow-2.3.0.dist-info/top_level.txt
iaflow-2.3.0.dist-info/RECORD
