Metadata-Version: 2.1
Name: iaflow
Version: 2.3.0
Summary: This library help to create models with identifiers, checkpoints, logs and metadata automatically, in order to make the training process more efficient and traceable.
Home-page: https://github.com/enmanuelmag/iaflow
Author: Enmanuel Magallanes Pinargote
Author-email: enmanuelmag@cardor.dev
Classifier: Programming Language :: Python :: 3
Classifier: License :: OSI Approved :: MIT License
Classifier: Operating System :: OS Independent
Requires-Python: >=3.6
License-File: LICENSE
Requires-Dist: requests
Requires-Dist: discord-webhook
Requires-Dist: notifier-function
